{
  "tender_id": "1044478",
  "ref_no": "42.01.7300.157.07.006.24-1470 Date: 05-12-2024",
  "closing_date": "24-Dec-2024 12:00",
  "opening_date": "24-Dec-2024 12:00",
  "procuring_entity": "Syedpur O&M Division",
  "tender_status": "Contract Awarded",
  "ministry_name": "Ministry of Water Resources",
  "agency_name": "Bangladesh Water Development Board (BWDB)",
  "package_no": "Saidpur/Regulator-02",
  "lot_no": "& Construction of Weir cum Regulator cum Bridge at Chickly River under Saidpur O&M Division, BWDB, Saidpur, NIlphamari.",
  "zone": "Syedpur",
  "bidder_count": 6,
  "bidders": [
    {
      "serial": 1,
      "name": "Dockyard & Engineering Works Limited"
    },
    {
      "serial": 2,
      "name": "M. M. Builders & Engineers Ltd.(Sub Contractor/Consultant - View Details)"
    },
    {
      "serial": 3,
      "name": "M/S. Hassan & Brothers"
    },
    {
      "serial": 4,
      "name": "MAK JOINT VENTURE(JVCA - View Details)"
    },
    {
      "serial": 5,
      "name": "SME-NDE-JV(JVCA - View Details)"
    },
    {
      "serial": 6,
      "name": "Taher Brothers Ltd."
    }
  ],
  "award_winner": "M/S. HASSAN & BROTHERS",
  "award_amount": 362130000.0,
  "estimated_cost": 364700000.0,
  "winner_quoted": 0.0,
  "winner_discount_pct": 0.0
}